{"140-":{"count":262,"keywordTitle":"1500","imageUrl":{"src":"productimages/v5lrs4d3.pz3_IMG_01_2110088789570.jpg","title":"beymen Corneliani  Lacivert Puff Yelek _erkek","marka":"beymen"}},"13-":{"count":528,"keywordTitle":"yelek","imageUrl":{"src":"erkek-yelek-dik-yaka-regular-fit-sisme-yelek-lacivert-190526-yelek-xint-190526-70179-48-O.jpg","title":"xint dik yaka regular fit şişme yelek _erkek","marka":"xint"}},"97-":{"count":251,"keywordTitle":"beymen","imageUrl":{"src":"productimages/ymjdgbv5.ueu_IMG_01_2110089269774.jpg","title":"beymen Moncler Grenoble  Haki Puff Yelek _erkek","marka":"beymen"}},"138-":{"count":5,"keywordTitle":"900-1000","imageUrl":{"src":"491/775/productimages/2400405589328_1.jpg","title":"network lacivert-ekru kruvaze yaka ekose yelek _erkek","marka":"network"}},"139-":{"count":21,"keywordTitle":"1000-1500","imageUrl":{"src":"productimages/l2o0puys.vh0_IMG_01_2110085327218.jpg","title":"beymen Academia  Siyah Yelek _erkek","marka":"beymen"}},"204-":{"count":14,"keywordTitle":"network","imageUrl":{"src":"productimages/zygs40e0.3oe_IMG_01_8683798140350.jpg","title":"beymen Network  YELEK _erkek","marka":"beymen"}},"191-":{"count":40,"keywordTitle":"triko","imageUrl":{"src":"productimages/mntgzlf1.i0m_IMG_01_2400406681519.jpg","title":"beymen Network  Antrasit Triko Yelek _erkek","marka":"beymen"}},"7-":{"count":1,"keywordTitle":"kaban","imageUrl":{"src":"productimages/utwkgibw.n0n_IMG_01_2110089062696.jpg","title":"beymen Premiata 1st  Siyah İç Yelek Detaylı Organik Pamuk Kaban _erkek","marka":"beymen"}},"8-":{"count":1,"keywordTitle":"ceket","imageUrl":{"src":"productimages/1auvr4tk.mj3_IMG_01_2110090421031.jpg","title":"beymen Dolce&Gabbana  Siyah Kapüşonlu Yelek Detaylı Ceket _erkek","marka":"beymen"}},"189-":{"count":4,"keywordTitle":"ekose","imageUrl":{"src":"productimages/zaebixx0.ves_IMG_01_2400405589328.jpg","title":"beymen Network  Lacivert Ekru Ekoseli Yelek _erkek","marka":"beymen"}},"91-":{"count":36,"keywordTitle":"defacto","imageUrl":{"src":"768/X5287AZ_22AU_BG720_01_03.jpg","title":"defacto defacto fit slim fit yelek _erkek","marka":"defacto"}},"131-":{"count":33,"keywordTitle":"200-300","imageUrl":{"src":"mnresize/600/-/pim/productimages/20211/4944477/l_20211-s1ct43z8-crp_a.jpg","title":"lcwaikiki dar kalıp dokulu klasik yelek _erkek","marka":"lcwaikiki"}},"129-":{"count":6,"keywordTitle":"0-100","imageUrl":{"src":"768/L4884AZ_21AU_BK27_01_01.jpg","title":"defacto slim fit v yaka yelek üst _erkek","marka":"defacto"}},"133-":{"count":52,"keywordTitle":"400-500","imageUrl":{"src":"mnresize/600/-/pim/productimages/20221/5463575/l_20221-s21776z8-j1p_a.jpg","title":"lcwaikiki dik yaka fermuarlı ince erkek yelek _erkek","marka":"lcwaikiki"}},"132-":{"count":42,"keywordTitle":"300-400","imageUrl":{"src":"mnresize/600/-/pim/productimages/20222/5909295/l_20222-w26507z8-dcj_a.jpg","title":"lcwaikiki standart kalıp dik yaka erkek yelek _erkek","marka":"lcwaikiki"}},"134-":{"count":71,"keywordTitle":"500-600","imageUrl":{"src":"mnresize/600/-/pim/productimages/20212/5144068/l_20212-w12491z8-rfd_a.jpg","title":"lcwaikiki slim fit dik yaka kalın erkek yelek _erkek","marka":"lcwaikiki"}},"130-":{"count":6,"keywordTitle":"100-200","imageUrl":{"src":"mnresize/600/-/productimages/20192/1/3638382/l_20192-9w7342z8-hen_a.jpg","title":"lcwaikiki erkek yelek _erkek","marka":"lcwaikiki"}},"135-":{"count":23,"keywordTitle":"600-700","imageUrl":{"src":"mnresize/600/-/pim/productimages/20231/6188464/v1/l_20231-s31497z8-ucn-96-81-93-190_a.jpg","title":"lcwaikiki slim fit dik yaka erkek şişme yelek _erkek","marka":"lcwaikiki"}},"103-":{"count":9,"keywordTitle":"hm","imageUrl":{"src":"/a2/8f/a28fe75c8e1db39f4a4f3f19f0af9cda03c02996.jpg],origin[dam],category[],type[LOOKBOOK],res[y],hmver[1]&call=url[file:/product/main]","title":"hm regular fit dolgulu yelek _erkek","marka":"hm"}},"185-":{"count":1,"keywordTitle":"kargo","imageUrl":{"src":"/07/48/074894bfcbaf0d2e0137da61c9b46cd53fcd68c0.jpg],origin[dam],category[],type[LOOKBOOK],res[z],hmver[1]&call=url[file:/product/main]","title":"hm relaxed fit naylon kargo yelek _erkek","marka":"hm"}},"136-":{"count":9,"keywordTitle":"700-800","imageUrl":{"src":"/76/32/76325a51bd30bde13d2dbda7d32cb1cbfa292c22.jpg],origin[dam],category[],type[LOOKBOOK],res[y],hmver[1]&call=url[file:/product/main]","title":"hm regular fit dolgulu yelek _erkek","marka":"hm"}},"92-":{"count":7,"keywordTitle":"koton","imageUrl":{"src":"products/2022/11/10/2611590/86c8c8f7-911e-4e6e-95dc-0a946b26feb9_size624x818.jpg","title":"koton  basic polar yelek cep detaylı dik yaka fermuarlı _erkek","marka":"koton"}},"93-":{"count":176,"keywordTitle":"lcwaikiki","imageUrl":{"src":"mnresize/600/-/pim/productimages/20221/5763848/v2/l_20221-s2fm99z8-ct3_a.jpg","title":"lcwaikiki dar kalıp klasik erkek yelek _erkek","marka":"lcwaikiki"}},"137-":{"count":1,"keywordTitle":"800-900","imageUrl":{"src":"mnresize/600/-/pim/productimages/20211/4831957/l_20211-s19948z8-h7v_a.jpg","title":"lcwaikiki standart kalıp erkek yelek _erkek","marka":"lcwaikiki"}},"205-":{"count":10,"keywordTitle":"sementa","imageUrl":{"src":"fermuarli-dik-yakai-triko-yelek-acik-bej-vest-sementa-71786-15-B.jpg","title":"sementa fermuarlı dik yakalı triko yelek - açık bej _erkek","marka":"sementa"}},"114-":{"count":12,"keywordTitle":"tozlu","imageUrl":{"src":"Uploads/UrunResimleri/thumb/tas-erkek-kapusonlu-sisme-yelek-fb-831.jpg","title":"tozlu taş erkek kapüşonlu şişme yelek _erkek","marka":"tozlu"}},"113-":{"count":22,"keywordTitle":"xint","imageUrl":{"src":"erkek-yelek-dik-yaka-regular-fit-citcit-dugmeli-sisme-yelek-kbeyaz-190525-yelek-xint-190525-70142-48-O.jpg","title":"xint dik yaka regular fit çıtçıt düğmeli şişme yelek _erkek","marka":"xint"}},"110-":{"count":4,"keywordTitle":"zara","imageUrl":{"src":"/2022/V/0/2/p/1564/414/401/2/w/315/1564414401_6_1_1.jpg?ts=1643706451463","title":"zara SLIM FIT TAKIM YELEK LACİVERT _erkek","marka":"zara"}}}