[{"i":"15-","k":[[217,"15-"],[217,"45-"],[3,"51-"],[92,"64-"],[6,"176-"],[13,"20-"],[66,"172-"],[31,"46-"],[10,"136-"],[201,"55-"],[9,"179-"],[15,"37-"]]},{"i":"23-","k":[[117,"23-"],[32,"176-"],[23,"214-"],[1,"51-"],[61,"192-"],[1,"96-"],[85,"55-"],[31,"122-"],[28,"147-"],[25,"222-"],[1,"45-"]]},{"i":"25-","k":[[2,"108-"],[2,"25-"],[2,"51-"],[2,"96-"],[2,"128-"]]},{"i":"27-","k":[[7,"27-"],[5,"45-"],[5,"128-"],[2,"215-"],[2,"55-"],[2,"96-"]]},{"i":"31-","k":[[6,"108-"],[8,"31-"],[8,"51-"],[8,"128-"],[2,"59-"]]},{"i":"37-","k":[[37,"37-"],[23,"45-"],[11,"128-"],[3,"192-"],[1,"220-"],[1,"222-"],[11,"96-"],[1,"136-"],[15,"15-"],[25,"55-"]]},{"i":"45-","k":[[233,"108-"],[569,"45-"],[105,"51-"],[335,"128-"],[48,"157-"],[23,"37-"],[8,"54-"],[5,"27-"],[41,"215-"],[10,"59-"],[44,"46-"],[10,"121-"],[1,"187-"],[217,"15-"],[95,"64-"],[17,"176-"],[25,"20-"],[67,"172-"],[10,"136-"],[207,"55-"],[9,"179-"],[1,"23-"]]},{"i":"51-","k":[[137,"108-"],[105,"45-"],[156,"51-"],[147,"128-"],[6,"157-"],[2,"25-"],[29,"96-"],[8,"31-"],[4,"192-"],[1,"215-"],[4,"122-"],[2,"46-"],[2,"59-"],[6,"214-"],[3,"15-"],[4,"64-"],[9,"176-"],[1,"23-"],[4,"20-"]]},{"i":"55-","k":[[85,"23-"],[603,"55-"],[86,"122-"],[28,"147-"],[201,"15-"],[207,"45-"],[108,"64-"],[148,"172-"],[180,"20-"],[116,"192-"],[33,"179-"],[51,"46-"],[75,"214-"],[25,"37-"],[113,"96-"],[4,"121-"],[3,"178-"],[37,"222-"],[6,"129-"],[2,"95-"],[4,"221-"],[2,"27-"],[1,"63-"]]},{"i":"59-","k":[[10,"45-"],[12,"59-"],[12,"128-"],[2,"215-"],[1,"187-"],[2,"31-"],[2,"51-"]]},{"i":"63-","k":[[1,"20-"],[1,"55-"],[1,"63-"],[1,"192-"],[1,"222-"]]},{"i":"95-","k":[[2,"55-"],[2,"95-"],[1,"172-"],[1,"214-"],[1,"20-"],[1,"122-"]]},{"i":"121-","k":[[10,"45-"],[17,"121-"],[10,"128-"],[7,"96-"],[3,"136-"],[4,"55-"]]},{"i":"129-","k":[[5,"46-"],[6,"55-"],[6,"129-"],[1,"179-"],[1,"172-"]]},{"i":"147-","k":[[11,"108-"],[28,"23-"],[28,"55-"],[41,"122-"],[41,"147-"],[13,"177-"],[2,"157-"]]},{"i":"157-","k":[[48,"45-"],[6,"51-"],[50,"128-"],[52,"157-"],[12,"215-"],[1,"96-"],[1,"214-"],[2,"122-"],[2,"147-"],[2,"177-"]]},{"i":"177-","k":[[14,"108-"],[16,"177-"],[3,"192-"],[13,"122-"],[13,"147-"],[2,"157-"]]},{"i":"179-","k":[[9,"15-"],[9,"45-"],[33,"55-"],[14,"172-"],[33,"179-"],[9,"122-"],[10,"64-"],[13,"96-"],[7,"20-"],[2,"46-"],[1,"129-"],[1,"192-"],[1,"221-"]]},{"i":"187-","k":[[1,"45-"],[1,"59-"],[1,"128-"],[1,"187-"],[1,"215-"]]},{"i":"215-","k":[[25,"108-"],[2,"27-"],[41,"45-"],[41,"128-"],[41,"215-"],[12,"157-"],[2,"59-"],[1,"187-"],[1,"51-"]]},{"i":"221-","k":[[4,"55-"],[4,"96-"],[4,"172-"],[4,"221-"],[1,"179-"]]},{"i":"15-37-","k":[[15,"15-"],[15,"37-"],[15,"45-"],[15,"55-"]]},{"i":"15-45-","k":[[217,"15-"],[217,"45-"],[3,"51-"],[92,"64-"],[6,"176-"],[13,"20-"],[66,"172-"],[31,"46-"],[10,"136-"],[201,"55-"],[9,"179-"],[15,"37-"]]},{"i":"15-51-","k":[[3,"15-"],[3,"45-"],[3,"51-"],[1,"64-"],[3,"176-"],[2,"20-"]]},{"i":"15-55-","k":[[201,"15-"],[201,"45-"],[201,"55-"],[84,"64-"],[65,"172-"],[9,"179-"],[28,"46-"],[15,"37-"],[9,"20-"]]},{"i":"20-45-","k":[[25,"20-"],[25,"45-"],[12,"176-"],[13,"15-"],[2,"51-"],[13,"55-"],[1,"179-"]]},{"i":"20-51-","k":[[2,"15-"],[4,"20-"],[2,"45-"],[4,"51-"],[4,"176-"],[1,"96-"],[1,"122-"]]},{"i":"20-55-","k":[[180,"20-"],[180,"55-"],[69,"192-"],[34,"122-"],[42,"214-"],[7,"179-"],[3,"178-"],[12,"222-"],[13,"45-"],[9,"15-"],[22,"96-"],[1,"95-"],[1,"63-"]]},{"i":"20-63-","k":[[1,"20-"],[1,"55-"],[1,"63-"],[1,"192-"],[1,"222-"]]},{"i":"20-95-","k":[[1,"20-"],[1,"55-"],[1,"95-"],[1,"122-"]]},{"i":"23-45-","k":[[1,"23-"],[1,"45-"],[1,"55-"]]},{"i":"23-51-","k":[[1,"23-"],[1,"51-"],[1,"176-"],[1,"192-"]]},{"i":"23-55-","k":[[85,"23-"],[85,"55-"],[31,"122-"],[28,"147-"],[46,"192-"],[25,"222-"],[7,"214-"],[1,"45-"]]},{"i":"25-51-","k":[[2,"108-"],[2,"25-"],[2,"51-"],[2,"96-"],[2,"128-"]]},{"i":"27-45-","k":[[5,"27-"],[5,"45-"],[5,"128-"],[2,"215-"]]},{"i":"27-55-","k":[[2,"27-"],[2,"55-"],[2,"96-"]]},{"i":"31-51-","k":[[6,"108-"],[8,"31-"],[8,"51-"],[8,"128-"],[2,"59-"]]},{"i":"31-59-","k":[[2,"31-"],[2,"51-"],[2,"59-"],[2,"128-"]]},{"i":"37-45-","k":[[23,"37-"],[23,"45-"],[8,"128-"],[15,"15-"],[15,"55-"]]},{"i":"37-55-","k":[[15,"15-"],[25,"37-"],[15,"45-"],[25,"55-"],[10,"96-"]]},{"i":"45-51-","k":[[92,"108-"],[105,"45-"],[105,"51-"],[100,"128-"],[6,"157-"],[1,"215-"],[2,"46-"],[3,"15-"],[3,"64-"],[5,"176-"],[2,"20-"]]},{"i":"45-55-","k":[[201,"15-"],[207,"45-"],[207,"55-"],[85,"64-"],[65,"172-"],[9,"179-"],[28,"46-"],[15,"37-"],[13,"20-"],[1,"23-"]]},{"i":"45-59-","k":[[10,"45-"],[10,"59-"],[10,"128-"],[2,"215-"],[1,"187-"]]},{"i":"46-51-","k":[[2,"45-"],[2,"46-"],[2,"51-"],[2,"128-"]]},{"i":"46-55-","k":[[28,"15-"],[28,"45-"],[51,"46-"],[51,"55-"],[18,"96-"],[2,"179-"],[5,"129-"]]},{"i":"51-59-","k":[[2,"31-"],[2,"51-"],[2,"59-"],[2,"128-"]]},{"i":"55-63-","k":[[1,"20-"],[1,"55-"],[1,"63-"],[1,"192-"],[1,"222-"]]},{"i":"55-95-","k":[[2,"55-"],[2,"95-"],[1,"172-"],[1,"214-"],[1,"20-"],[1,"122-"]]},{"i":"15-179-","k":[[9,"15-"],[9,"45-"],[9,"55-"],[6,"172-"],[9,"179-"],[2,"64-"],[1,"20-"]]},{"i":"20-179-","k":[[7,"20-"],[7,"55-"],[5,"122-"],[7,"179-"],[1,"192-"],[1,"15-"],[1,"45-"]]},{"i":"23-147-","k":[[28,"23-"],[28,"55-"],[28,"122-"],[28,"147-"]]},{"i":"27-215-","k":[[2,"27-"],[2,"45-"],[2,"128-"],[2,"215-"]]},{"i":"45-121-","k":[[10,"45-"],[10,"121-"],[10,"128-"]]},{"i":"45-157-","k":[[48,"45-"],[6,"51-"],[48,"128-"],[48,"157-"],[12,"215-"]]},{"i":"45-179-","k":[[9,"15-"],[9,"45-"],[9,"55-"],[6,"172-"],[9,"179-"],[2,"64-"],[1,"20-"]]},{"i":"45-187-","k":[[1,"45-"],[1,"59-"],[1,"128-"],[1,"187-"],[1,"215-"]]},{"i":"45-215-","k":[[25,"108-"],[2,"27-"],[41,"45-"],[41,"128-"],[41,"215-"],[12,"157-"],[2,"59-"],[1,"187-"],[1,"51-"]]},{"i":"46-129-","k":[[5,"46-"],[5,"55-"],[5,"129-"],[1,"179-"]]},{"i":"46-179-","k":[[2,"46-"],[2,"55-"],[1,"96-"],[2,"179-"],[1,"129-"]]},{"i":"51-157-","k":[[6,"45-"],[6,"51-"],[6,"128-"],[6,"157-"],[1,"215-"]]},{"i":"51-215-","k":[[1,"45-"],[1,"51-"],[1,"128-"],[1,"157-"],[1,"215-"]]},{"i":"55-121-","k":[[4,"55-"],[4,"96-"],[4,"121-"]]},{"i":"55-129-","k":[[5,"46-"],[6,"55-"],[6,"129-"],[1,"179-"],[1,"172-"]]},{"i":"55-147-","k":[[28,"23-"],[28,"55-"],[28,"122-"],[28,"147-"]]},{"i":"55-179-","k":[[9,"15-"],[9,"45-"],[33,"55-"],[14,"172-"],[33,"179-"],[9,"122-"],[10,"64-"],[13,"96-"],[7,"20-"],[2,"46-"],[1,"129-"],[1,"192-"],[1,"221-"]]},{"i":"55-221-","k":[[4,"55-"],[4,"96-"],[4,"172-"],[4,"221-"],[1,"179-"]]},{"i":"59-187-","k":[[1,"45-"],[1,"59-"],[1,"128-"],[1,"187-"],[1,"215-"]]},{"i":"59-215-","k":[[2,"45-"],[2,"59-"],[2,"128-"],[2,"215-"],[1,"187-"]]},{"i":"64-179-","k":[[10,"55-"],[10,"64-"],[8,"96-"],[10,"179-"],[2,"15-"],[2,"45-"]]},{"i":"96-121-","k":[[7,"96-"],[7,"121-"],[3,"136-"],[4,"55-"]]},{"i":"96-157-","k":[[1,"96-"],[1,"128-"],[1,"157-"]]},{"i":"96-179-","k":[[13,"55-"],[8,"64-"],[13,"96-"],[13,"179-"],[1,"46-"],[4,"172-"],[1,"221-"]]},{"i":"96-221-","k":[[4,"55-"],[4,"96-"],[4,"172-"],[4,"221-"],[1,"179-"]]},{"i":"108-147-","k":[[11,"108-"],[11,"122-"],[11,"147-"],[11,"177-"]]},{"i":"108-177-","k":[[14,"108-"],[14,"177-"],[3,"192-"],[11,"122-"],[11,"147-"]]},{"i":"108-215-","k":[[25,"108-"],[25,"45-"],[25,"128-"],[25,"215-"]]},{"i":"122-147-","k":[[11,"108-"],[28,"23-"],[28,"55-"],[41,"122-"],[41,"147-"],[13,"177-"],[2,"157-"]]},{"i":"122-157-","k":[[2,"122-"],[2,"147-"],[2,"157-"],[2,"177-"]]},{"i":"122-177-","k":[[11,"108-"],[13,"122-"],[13,"147-"],[13,"177-"],[2,"157-"]]},{"i":"122-179-","k":[[9,"55-"],[9,"122-"],[4,"172-"],[9,"179-"],[5,"20-"]]},{"i":"128-157-","k":[[48,"45-"],[6,"51-"],[50,"128-"],[50,"157-"],[12,"215-"],[1,"96-"],[1,"214-"]]},{"i":"128-187-","k":[[1,"45-"],[1,"59-"],[1,"128-"],[1,"187-"],[1,"215-"]]},{"i":"128-215-","k":[[25,"108-"],[2,"27-"],[41,"45-"],[41,"128-"],[41,"215-"],[12,"157-"],[2,"59-"],[1,"187-"],[1,"51-"]]},{"i":"129-179-","k":[[1,"46-"],[1,"55-"],[1,"129-"],[1,"179-"]]},{"i":"147-157-","k":[[2,"122-"],[2,"147-"],[2,"157-"],[2,"177-"]]},{"i":"147-177-","k":[[11,"108-"],[13,"122-"],[13,"147-"],[13,"177-"],[2,"157-"]]},{"i":"15-20-45-","k":[[13,"15-"],[13,"20-"],[13,"45-"],[2,"51-"],[4,"176-"],[9,"55-"],[1,"179-"]]},{"i":"15-20-51-","k":[[2,"15-"],[2,"20-"],[2,"45-"],[2,"51-"],[2,"176-"]]},{"i":"15-20-55-","k":[[9,"15-"],[9,"20-"],[9,"45-"],[9,"55-"],[1,"179-"]]},{"i":"15-37-45-","k":[[15,"15-"],[15,"37-"],[15,"45-"],[15,"55-"]]},{"i":"15-37-55-","k":[[15,"15-"],[15,"37-"],[15,"45-"],[15,"55-"]]},{"i":"15-45-51-","k":[[3,"15-"],[3,"45-"],[3,"51-"],[1,"64-"],[3,"176-"],[2,"20-"]]},{"i":"15-45-55-","k":[[201,"15-"],[201,"45-"],[201,"55-"],[84,"64-"],[65,"172-"],[9,"179-"],[28,"46-"],[15,"37-"],[9,"20-"]]},{"i":"15-46-55-","k":[[28,"15-"],[28,"45-"],[28,"46-"],[28,"55-"]]},{"i":"157-177-","k":[[2,"122-"],[2,"147-"],[2,"157-"],[2,"177-"]]},{"i":"157-215-","k":[[12,"45-"],[12,"128-"],[12,"157-"],[12,"215-"],[1,"51-"]]},{"i":"172-179-","k":[[6,"15-"],[6,"45-"],[14,"55-"],[14,"172-"],[14,"179-"],[4,"122-"],[4,"96-"],[1,"221-"]]},{"i":"172-221-","k":[[4,"55-"],[4,"96-"],[4,"172-"],[4,"221-"],[1,"179-"]]},{"i":"179-221-","k":[[1,"55-"],[1,"96-"],[1,"172-"],[1,"179-"],[1,"221-"]]},{"i":"187-215-","k":[[1,"45-"],[1,"59-"],[1,"128-"],[1,"187-"],[1,"215-"]]},{"i":"20-45-51-","k":[[2,"15-"],[2,"20-"],[2,"45-"],[2,"51-"],[2,"176-"]]},{"i":"20-45-55-","k":[[13,"20-"],[13,"45-"],[13,"55-"],[9,"15-"],[1,"179-"]]},{"i":"20-55-63-","k":[[1,"20-"],[1,"55-"],[1,"63-"],[1,"192-"],[1,"222-"]]},{"i":"20-55-95-","k":[[1,"20-"],[1,"55-"],[1,"95-"],[1,"122-"]]},{"i":"23-45-55-","k":[[1,"23-"],[1,"45-"],[1,"55-"]]},{"i":"31-51-59-","k":[[2,"31-"],[2,"51-"],[2,"59-"],[2,"128-"]]},{"i":"37-45-55-","k":[[15,"15-"],[15,"37-"],[15,"45-"],[15,"55-"]]},{"i":"45-46-51-","k":[[2,"45-"],[2,"46-"],[2,"51-"],[2,"128-"]]},{"i":"45-46-55-","k":[[28,"15-"],[28,"45-"],[28,"46-"],[28,"55-"]]},{"i":"15-20-179-","k":[[1,"15-"],[1,"20-"],[1,"45-"],[1,"55-"],[1,"179-"]]},{"i":"15-45-179-","k":[[9,"15-"],[9,"45-"],[9,"55-"],[6,"172-"],[9,"179-"],[2,"64-"],[1,"20-"]]},{"i":"15-55-179-","k":[[9,"15-"],[9,"45-"],[9,"55-"],[6,"172-"],[9,"179-"],[2,"64-"],[1,"20-"]]},{"i":"15-64-179-","k":[[2,"15-"],[2,"45-"],[2,"55-"],[2,"64-"],[2,"179-"]]},{"i":"20-45-179-","k":[[1,"15-"],[1,"20-"],[1,"45-"],[1,"55-"],[1,"179-"]]},{"i":"20-55-179-","k":[[7,"20-"],[7,"55-"],[5,"122-"],[7,"179-"],[1,"192-"],[1,"15-"],[1,"45-"]]},{"i":"23-55-147-","k":[[28,"23-"],[28,"55-"],[28,"122-"],[28,"147-"]]},{"i":"27-45-215-","k":[[2,"27-"],[2,"45-"],[2,"128-"],[2,"215-"]]},{"i":"45-51-157-","k":[[6,"45-"],[6,"51-"],[6,"128-"],[6,"157-"],[1,"215-"]]},{"i":"45-51-215-","k":[[1,"45-"],[1,"51-"],[1,"128-"],[1,"157-"],[1,"215-"]]},{"i":"45-55-179-","k":[[9,"15-"],[9,"45-"],[9,"55-"],[6,"172-"],[9,"179-"],[2,"64-"],[1,"20-"]]},{"i":"45-59-187-","k":[[1,"45-"],[1,"59-"],[1,"128-"],[1,"187-"],[1,"215-"]]},{"i":"45-59-215-","k":[[2,"45-"],[2,"59-"],[2,"128-"],[2,"215-"],[1,"187-"]]},{"i":"45-64-179-","k":[[2,"15-"],[2,"45-"],[2,"55-"],[2,"64-"],[2,"179-"]]},{"i":"46-55-129-","k":[[5,"46-"],[5,"55-"],[5,"129-"],[1,"179-"]]},{"i":"46-55-179-","k":[[2,"46-"],[2,"55-"],[1,"96-"],[2,"179-"],[1,"129-"]]},{"i":"46-96-179-","k":[[1,"46-"],[1,"55-"],[1,"96-"],[1,"179-"]]},{"i":"55-64-179-","k":[[10,"55-"],[10,"64-"],[8,"96-"],[10,"179-"],[2,"15-"],[2,"45-"]]},{"i":"55-96-121-","k":[[4,"55-"],[4,"96-"],[4,"121-"]]},{"i":"55-96-179-","k":[[13,"55-"],[8,"64-"],[13,"96-"],[13,"179-"],[1,"46-"],[4,"172-"],[1,"221-"]]},{"i":"55-96-221-","k":[[4,"55-"],[4,"96-"],[4,"172-"],[4,"221-"],[1,"179-"]]},{"i":"64-96-179-","k":[[8,"55-"],[8,"64-"],[8,"96-"],[8,"179-"]]},{"i":"15-172-179-","k":[[6,"15-"],[6,"45-"],[6,"55-"],[6,"172-"],[6,"179-"]]},{"i":"15-20-45-51-","k":[[2,"15-"],[2,"20-"],[2,"45-"],[2,"51-"],[2,"176-"]]},{"i":"15-20-45-55-","k":[[9,"15-"],[9,"20-"],[9,"45-"],[9,"55-"],[1,"179-"]]},{"i":"15-37-45-55-","k":[[15,"15-"],[15,"37-"],[15,"45-"],[15,"55-"]]},{"i":"15-45-46-55-","k":[[28,"15-"],[28,"45-"],[28,"46-"],[28,"55-"]]},{"i":"20-122-179-","k":[[5,"20-"],[5,"55-"],[5,"122-"],[5,"179-"]]},{"i":"23-122-147-","k":[[28,"23-"],[28,"55-"],[28,"122-"],[28,"147-"]]},{"i":"27-128-215-","k":[[2,"27-"],[2,"45-"],[2,"128-"],[2,"215-"]]},{"i":"45-108-215-","k":[[25,"108-"],[25,"45-"],[25,"128-"],[25,"215-"]]},{"i":"45-128-157-","k":[[48,"45-"],[6,"51-"],[48,"128-"],[48,"157-"],[12,"215-"]]},{"i":"45-128-187-","k":[[1,"45-"],[1,"59-"],[1,"128-"],[1,"187-"],[1,"215-"]]},{"i":"45-128-215-","k":[[25,"108-"],[2,"27-"],[41,"45-"],[41,"128-"],[41,"215-"],[12,"157-"],[2,"59-"],[1,"187-"],[1,"51-"]]},{"i":"45-157-215-","k":[[12,"45-"],[12,"128-"],[12,"157-"],[12,"215-"],[1,"51-"]]},{"i":"45-172-179-","k":[[6,"15-"],[6,"45-"],[6,"55-"],[6,"172-"],[6,"179-"]]},{"i":"45-187-215-","k":[[1,"45-"],[1,"59-"],[1,"128-"],[1,"187-"],[1,"215-"]]},{"i":"46-129-179-","k":[[1,"46-"],[1,"55-"],[1,"129-"],[1,"179-"]]},{"i":"51-128-157-","k":[[6,"45-"],[6,"51-"],[6,"128-"],[6,"157-"],[1,"215-"]]},{"i":"51-128-215-","k":[[1,"45-"],[1,"51-"],[1,"128-"],[1,"157-"],[1,"215-"]]},{"i":"51-157-215-","k":[[1,"45-"],[1,"51-"],[1,"128-"],[1,"157-"],[1,"215-"]]},{"i":"55-122-147-","k":[[28,"23-"],[28,"55-"],[28,"122-"],[28,"147-"]]},{"i":"55-122-179-","k":[[9,"55-"],[9,"122-"],[4,"172-"],[9,"179-"],[5,"20-"]]},{"i":"55-129-179-","k":[[1,"46-"],[1,"55-"],[1,"129-"],[1,"179-"]]},{"i":"55-172-179-","k":[[6,"15-"],[6,"45-"],[14,"55-"],[14,"172-"],[14,"179-"],[4,"122-"],[4,"96-"],[1,"221-"]]},{"i":"55-172-221-","k":[[4,"55-"],[4,"96-"],[4,"172-"],[4,"221-"],[1,"179-"]]},{"i":"55-179-221-","k":[[1,"55-"],[1,"96-"],[1,"172-"],[1,"179-"],[1,"221-"]]},{"i":"59-128-187-","k":[[1,"45-"],[1,"59-"],[1,"128-"],[1,"187-"],[1,"215-"]]},{"i":"59-128-215-","k":[[2,"45-"],[2,"59-"],[2,"128-"],[2,"215-"],[1,"187-"]]},{"i":"59-187-215-","k":[[1,"45-"],[1,"59-"],[1,"128-"],[1,"187-"],[1,"215-"]]},{"i":"96-128-157-","k":[[1,"96-"],[1,"128-"],[1,"157-"]]},{"i":"96-172-179-","k":[[4,"55-"],[4,"96-"],[4,"172-"],[4,"179-"],[1,"221-"]]},{"i":"96-172-221-","k":[[4,"55-"],[4,"96-"],[4,"172-"],[4,"221-"],[1,"179-"]]},{"i":"96-179-221-","k":[[1,"55-"],[1,"96-"],[1,"172-"],[1,"179-"],[1,"221-"]]},{"i":"108-122-147-","k":[[11,"108-"],[11,"122-"],[11,"147-"],[11,"177-"]]},{"i":"108-122-177-","k":[[11,"108-"],[11,"122-"],[11,"147-"],[11,"177-"]]},{"i":"108-128-215-","k":[[25,"108-"],[25,"45-"],[25,"128-"],[25,"215-"]]},{"i":"108-147-177-","k":[[11,"108-"],[11,"122-"],[11,"147-"],[11,"177-"]]},{"i":"122-147-157-","k":[[2,"122-"],[2,"147-"],[2,"157-"],[2,"177-"]]},{"i":"122-147-177-","k":[[11,"108-"],[13,"122-"],[13,"147-"],[13,"177-"],[2,"157-"]]},{"i":"122-157-177-","k":[[2,"122-"],[2,"147-"],[2,"157-"],[2,"177-"]]},{"i":"122-172-179-","k":[[4,"55-"],[4,"122-"],[4,"172-"],[4,"179-"]]},{"i":"128-157-215-","k":[[12,"45-"],[12,"128-"],[12,"157-"],[12,"215-"],[1,"51-"]]},{"i":"128-187-215-","k":[[1,"45-"],[1,"59-"],[1,"128-"],[1,"187-"],[1,"215-"]]},{"i":"147-157-177-","k":[[2,"122-"],[2,"147-"],[2,"157-"],[2,"177-"]]},{"i":"15-20-45-179-","k":[[1,"15-"],[1,"20-"],[1,"45-"],[1,"55-"],[1,"179-"]]},{"i":"15-20-55-179-","k":[[1,"15-"],[1,"20-"],[1,"45-"],[1,"55-"],[1,"179-"]]},{"i":"15-45-55-179-","k":[[9,"15-"],[9,"45-"],[9,"55-"],[6,"172-"],[9,"179-"],[2,"64-"],[1,"20-"]]},{"i":"15-45-64-179-","k":[[2,"15-"],[2,"45-"],[2,"55-"],[2,"64-"],[2,"179-"]]},{"i":"15-55-64-179-","k":[[2,"15-"],[2,"45-"],[2,"55-"],[2,"64-"],[2,"179-"]]},{"i":"172-179-221-","k":[[1,"55-"],[1,"96-"],[1,"172-"],[1,"179-"],[1,"221-"]]},{"i":"20-45-55-179-","k":[[1,"15-"],[1,"20-"],[1,"45-"],[1,"55-"],[1,"179-"]]},{"i":"45-55-64-179-","k":[[2,"15-"],[2,"45-"],[2,"55-"],[2,"64-"],[2,"179-"]]},{"i":"46-55-96-179-","k":[[1,"46-"],[1,"55-"],[1,"96-"],[1,"179-"]]},{"i":"55-64-96-179-","k":[[8,"55-"],[8,"64-"],[8,"96-"],[8,"179-"]]},{"i":"15-45-172-179-","k":[[6,"15-"],[6,"45-"],[6,"55-"],[6,"172-"],[6,"179-"]]},{"i":"15-55-172-179-","k":[[6,"15-"],[6,"45-"],[6,"55-"],[6,"172-"],[6,"179-"]]},{"i":"20-55-122-179-","k":[[5,"20-"],[5,"55-"],[5,"122-"],[5,"179-"]]},{"i":"23-55-122-147-","k":[[28,"23-"],[28,"55-"],[28,"122-"],[28,"147-"]]},{"i":"27-45-128-215-","k":[[2,"27-"],[2,"45-"],[2,"128-"],[2,"215-"]]},{"i":"45-51-128-157-","k":[[6,"45-"],[6,"51-"],[6,"128-"],[6,"157-"],[1,"215-"]]},{"i":"45-51-128-215-","k":[[1,"45-"],[1,"51-"],[1,"128-"],[1,"157-"],[1,"215-"]]},{"i":"45-51-157-215-","k":[[1,"45-"],[1,"51-"],[1,"128-"],[1,"157-"],[1,"215-"]]},{"i":"45-55-172-179-","k":[[6,"15-"],[6,"45-"],[6,"55-"],[6,"172-"],[6,"179-"]]},{"i":"45-59-128-187-","k":[[1,"45-"],[1,"59-"],[1,"128-"],[1,"187-"],[1,"215-"]]},{"i":"45-59-128-215-","k":[[2,"45-"],[2,"59-"],[2,"128-"],[2,"215-"],[1,"187-"]]},{"i":"45-59-187-215-","k":[[1,"45-"],[1,"59-"],[1,"128-"],[1,"187-"],[1,"215-"]]},{"i":"46-55-129-179-","k":[[1,"46-"],[1,"55-"],[1,"129-"],[1,"179-"]]},{"i":"55-96-172-179-","k":[[4,"55-"],[4,"96-"],[4,"172-"],[4,"179-"],[1,"221-"]]},{"i":"55-96-172-221-","k":[[4,"55-"],[4,"96-"],[4,"172-"],[4,"221-"],[1,"179-"]]},{"i":"55-96-179-221-","k":[[1,"55-"],[1,"96-"],[1,"172-"],[1,"179-"],[1,"221-"]]},{"i":"15-20-45-55-179-","k":[[1,"15-"],[1,"20-"],[1,"45-"],[1,"55-"],[1,"179-"]]},{"i":"15-45-55-64-179-","k":[[2,"15-"],[2,"45-"],[2,"55-"],[2,"64-"],[2,"179-"]]},{"i":"45-108-128-215-","k":[[25,"108-"],[25,"45-"],[25,"128-"],[25,"215-"]]},{"i":"45-128-157-215-","k":[[12,"45-"],[12,"128-"],[12,"157-"],[12,"215-"],[1,"51-"]]},{"i":"45-128-187-215-","k":[[1,"45-"],[1,"59-"],[1,"128-"],[1,"187-"],[1,"215-"]]},{"i":"51-128-157-215-","k":[[1,"45-"],[1,"51-"],[1,"128-"],[1,"157-"],[1,"215-"]]},{"i":"55-122-172-179-","k":[[4,"55-"],[4,"122-"],[4,"172-"],[4,"179-"]]},{"i":"55-172-179-221-","k":[[1,"55-"],[1,"96-"],[1,"172-"],[1,"179-"],[1,"221-"]]},{"i":"59-128-187-215-","k":[[1,"45-"],[1,"59-"],[1,"128-"],[1,"187-"],[1,"215-"]]},{"i":"96-172-179-221-","k":[[1,"55-"],[1,"96-"],[1,"172-"],[1,"179-"],[1,"221-"]]},{"i":"108-122-147-177-","k":[[11,"108-"],[11,"122-"],[11,"147-"],[11,"177-"]]},{"i":"122-147-157-177-","k":[[2,"122-"],[2,"147-"],[2,"157-"],[2,"177-"]]},{"i":"15-45-55-172-179-","k":[[6,"15-"],[6,"45-"],[6,"55-"],[6,"172-"],[6,"179-"]]},{"i":"45-51-128-157-215-","k":[[1,"45-"],[1,"51-"],[1,"128-"],[1,"157-"],[1,"215-"]]},{"i":"45-59-128-187-215-","k":[[1,"45-"],[1,"59-"],[1,"128-"],[1,"187-"],[1,"215-"]]},{"i":"55-96-172-179-221-","k":[[1,"55-"],[1,"96-"],[1,"172-"],[1,"179-"],[1,"221-"]]}]