{"57-":{"count":10,"keywordTitle":"1500","imageUrl":{"src":"480/720/pentiimages/PY5Q348922IY-76_front.jpg","title":"penti haki erkek çocuk dinozor terlik _ecocuk","marka":"penti"}},"33-":{"count":65,"keywordTitle":"terlik","imageUrl":{"src":"768/Y4308A6_22WN_BE1_01_01.jpg","title":"defacto erkek çocuk düz taban ev terliği _ecocuk","marka":"defacto"}},"164-":{"count":32,"keywordTitle":"beymen","imageUrl":{"src":"productimages/5olgiipg.orj_IMG_01_2110087724916.jpg","title":"beymen Havaianas  Top Camu Açık Yeşil Unisex Çocuk Plaj Terliği _ecocuk","marka":"beymen"}},"124-":{"count":2,"keywordTitle":"deri","imageUrl":{"src":"768/X4802A6_22SM_WT34_01_01.jpg","title":"defacto erkek çocuk nasa düz taban suni deri terlik _ecocuk","marka":"defacto"}},"80-":{"count":20,"keywordTitle":"400-500","imageUrl":{"src":"productimages/c2nucj1s.qv4_IMG_01_2110087724411.jpg","title":"beymen Havaianas  Disney Cool Unisex Çocuk Plaj Terliği _ecocuk","marka":"beymen"}},"92-":{"count":6,"keywordTitle":"300-400","imageUrl":{"src":"/bc/b0/bcb07710e72e3abea169a914cdec622b514b801f.jpg],origin[dam],category[],type[DESCRIPTIVESTILLLIFE],res[z],hmver[2]&call=url[file:/product/main]","title":"hm yumuşak ev terliği _ecocuk","marka":"hm"}},"93-":{"count":1,"keywordTitle":"500-600","imageUrl":{"src":"productimages/w2v1ccrw.dld_IMG_01_2110087725364.jpg","title":"beymen Havaianas  Top Pokemon Sarı Unisex Çocuk Plaj Terliği _ecocuk","marka":"beymen"}},"28-":{"count":28,"keywordTitle":"defacto","imageUrl":{"src":"768/T4055A6_22SM_BE278_01_01.jpg","title":"defacto erkek çocuk desenli plaj sandalet terlik _ecocuk","marka":"defacto"}},"69-":{"count":19,"keywordTitle":"0-100","imageUrl":{"src":"768/T4055A6_22SM_KH3_01_01.jpg","title":"defacto erkek çocuk desenli plaj sandalet terlik _ecocuk","marka":"defacto"}},"43-":{"count":9,"keywordTitle":"100-200","imageUrl":{"src":"768/T4054A6_NS_BE278_01_01.jpg","title":"defacto erkek çocuk eva çift bant tokalı terlik _ecocuk","marka":"defacto"}},"160-":{"count":6,"keywordTitle":"sandalet","imageUrl":{"src":"768/T4055A6_22SM_OG143_01_01.jpg","title":"defacto erkek çocuk desenli plaj sandalet terlik _ecocuk","marka":"defacto"}},"105-":{"count":3,"keywordTitle":"hm","imageUrl":{"src":"/d9/a1/d9a15c6d8f4be87a3723768f82dd9b9d9f3d8933.jpg],origin[dam],category[kids_boys_shoes_slippers],type[DESCRIPTIVESTILLLIFE],res[y],hmver[2]&call=url[file:/product/main]","title":"hm yumuşak ev terliği _ecocuk","marka":"hm"}},"40-":{"count":2,"keywordTitle":"penti","imageUrl":{"src":"480/720/pentiimages/PY5Q348922IY-76_front.jpg","title":"penti haki erkek çocuk dinozor terlik _ecocuk","marka":"penti"}}}