{"57-":{"count":36,"keywordTitle":"1500","imageUrl":{"src":"491/775/productimages/8683798058990_1.jpg","title":"network camel manto _kadin","marka":"network"}},"5-":{"count":47,"keywordTitle":"manto","imageUrl":{"src":"491/775/productimages/8683798161614_1.jpg","title":"network vizon yün karışımlı yün manto _kadin","marka":"network"}},"164-":{"count":10,"keywordTitle":"beymen","imageUrl":{"src":"productimages/2fcod4m3.nfb_IMG_01_8683798059294.jpg","title":"beymen Network  Regular Fit Siyah Ekoseli Manto _kadin","marka":"beymen"}},"204-":{"count":35,"keywordTitle":"network","imageUrl":{"src":"491/775/productimages/8683798058846_1.jpg","title":"network kırmızı manto _kadin","marka":"network"}},"65-":{"count":2,"keywordTitle":"ekose","imageUrl":{"src":"productimages/2fcod4m3.nfb_IMG_01_8683798059294.jpg","title":"beymen Network  Regular Fit Siyah Ekoseli Manto _kadin","marka":"beymen"}},"53-":{"count":11,"keywordTitle":"dilvin","imageUrl":{"src":"123111/middle/101a06824_fusya-1.jpg","title":"dilvin 6824 uzun peluş manto fuşya _kadin","marka":"dilvin"}},"131-":{"count":11,"keywordTitle":"uzun","imageUrl":{"src":"117903/middle/101a06824_koyubej.jpg","title":"dilvin 6824 uzun peluş manto koyu bej _kadin","marka":"dilvin"}},"135-":{"count":8,"keywordTitle":"900-1000","imageUrl":{"src":"118220/middle/101a06824_bebemavi-1.jpg","title":"dilvin 6824 uzun peluş manto bebe mavi _kadin","marka":"dilvin"}},"146-":{"count":3,"keywordTitle":"800-900","imageUrl":{"src":"122915/middle/101a06824_zumrut-.jpg","title":"dilvin 6824 uzun peluş manto zümrüt _kadin","marka":"dilvin"}},"197-":{"count":1,"keywordTitle":"vakko","imageUrl":{"src":"2022/08/25/1368243/3a6d4579-a4a6-46f9-960a-2c0331cc4882_size500x762_quality100_cropCenter.jpg","title":"vakko manto _kadin","marka":"vakko"}}}