{"140-":{"count":291,"keywordTitle":"1500","imageUrl":{"src":"productimages/fizgpfkz.shn_IMG_01_8683798057795.jpg","title":"beymen Network  Regular Fit Camel Deri Kaban _kadin","marka":"beymen"}},"7-":{"count":735,"keywordTitle":"kaban","imageUrl":{"src":"Uploads/UrunResimleri/thumb/kadin-buklet-tek-dugmeli-cepli-kaban-k-bf-a4b.jpg","title":"tozlu kadın buklet tek düğmeli cepli kaban kiremit _kadin","marka":"tozlu"}},"96-":{"count":10,"keywordTitle":"baqa","imageUrl":{"src":"/Uploads/UrunResimleri/thumb/qw2347032-biye-detayli-ekru-kaban-baqa-9f4e-e.jpg","title":"baqa biye detaylı ekru kaban _kadin","marka":"baqa"}},"181-":{"count":59,"keywordTitle":"oversize","imageUrl":{"src":"products/2022/12/14/2616993/d714b61f-43e4-4d09-9f6b-c4b933a87d34_size624x818.jpg","title":"koton  melis ağazat x koton - yakası çıkarılabilir peluş detaylı kruvaze oversize kısa kaban _kadin","marka":"koton"}},"97-":{"count":74,"keywordTitle":"beymen","imageUrl":{"src":"productimages/ji5nczac.glj_IMG_01_2110087787669.jpg","title":"beymen Beymen Club  Oversize Mint Kruvaze Peluş Kaban _kadin","marka":"beymen"}},"90-":{"count":57,"keywordTitle":"uzun","imageUrl":{"src":"mnresize/-/750/g2150siyah_1.jpeg","title":"patirti kapşonlu uzun siyah kadın şişme kaban _kadin","marka":"patirti"}},"204-":{"count":43,"keywordTitle":"network","imageUrl":{"src":"491/775/productimages/2400406703877_1.jpg","title":"network vizon kaban _kadin","marka":"network"}},"189-":{"count":14,"keywordTitle":"ekose","imageUrl":{"src":"productimages/ow3zlbbb.vau_IMG_01_2110089151345.jpg","title":"beymen Etoile Isabel Marant  Ekose Desenli Yün Kaban _kadin","marka":"beymen"}},"98-":{"count":5,"keywordTitle":"beyyoglu","imageUrl":{"src":"2023/01/05/52000/4f765181-6d61-48d4-af69-9e2ceb649b20_size720x1080.jpg","title":"beyyoglu yün karışımlı kaşe biker kaban _kadin","marka":"beyyoglu"}},"139-":{"count":141,"keywordTitle":"1000-1500","imageUrl":{"src":"products/2022/12/01/2629120/f9deb9cc-a8ad-442c-8244-902935fdda1f_size624x818.jpg","title":"koton  anvelop kaşe kaban kuşaklı fleto cep detaylı _kadin","marka":"koton"}},"99-":{"count":13,"keywordTitle":"colins","imageUrl":{"src":"800/-/Assets/Branch/Originals/135953_0.jpeg","title":"colins  regular fir kapüşonlu çok cepli kırmızı kadın kaban _kadin","marka":"colins"}},"138-":{"count":64,"keywordTitle":"900-1000","imageUrl":{"src":"mnresize/-/750/g3077lacivert_1.jpeg","title":"patirti içi yünlü keten kaban _kadin","marka":"patirti"}},"136-":{"count":71,"keywordTitle":"700-800","imageUrl":{"src":"products/2022/12/08/2627809/ffe7d675-2f59-4de9-b745-a54e699a18ac_size624x818.jpg","title":"koton  kapüşonlu oversize peluş kısa kaban _kadin","marka":"koton"}},"134-":{"count":36,"keywordTitle":"500-600","imageUrl":{"src":"mnresize/-/750/isk54siyah_1.jpeg","title":"patirti kapşonlu oversize kadın şişme kaban _kadin","marka":"patirti"}},"91-":{"count":12,"keywordTitle":"defacto","imageUrl":{"src":"768/U7644AZ_21WN_BN67_01_01.jpg","title":"defacto suni kürk cep detaylı çıtçıtlı relax fit midi kaban _kadin","marka":"defacto"}},"132-":{"count":8,"keywordTitle":"300-400","imageUrl":{"src":"Uploads/UrunResimleri/thumb/kadin-on-dugmeli-buklet-kaban-yesil-49-cf-cb5.jpg","title":"tozlu kadın ön düğmeli buklet kaban yeşil _kadin","marka":"tozlu"}},"5-":{"count":8,"keywordTitle":"mont","imageUrl":{"src":"768/A2109AX_22WN_BK27_01_01.jpg","title":"defacto isı yalıtımlı su geçirmez suni kürklü kapüşonlu kaban mont _kadin","marka":"defacto"}},"137-":{"count":61,"keywordTitle":"800-900","imageUrl":{"src":"mnresize/-/750/g2150vizon_1.jpeg","title":"patirti kapşonlu uzun kadın şişme kaban _kadin","marka":"patirti"}},"88-":{"count":15,"keywordTitle":"midi","imageUrl":{"src":"products/2022/10/12/2596851/adde23dc-4409-4ba7-99f2-34c50d325c23_size624x818.jpg","title":"koton midi boy kaşe kaban kruvaze düğmeli _kadin","marka":"koton"}},"103-":{"count":34,"keywordTitle":"hm","imageUrl":{"src":"/84/52/8452b0a51acce51ab5efcf10802f8f391d310495.jpg],origin[dam],category[],type[LOOKBOOK],res[y],hmver[1]&call=url[file:/product/main]","title":"hm kaban _kadin","marka":"hm"}},"133-":{"count":30,"keywordTitle":"400-500","imageUrl":{"src":"products/2023/01/03/2645384/d2489cbe-36b6-49fa-b3b6-7e92908e8fe1_size624x818.jpg","title":"koton  buklet kaban cepli düğmeli ceket yaka _kadin","marka":"koton"}},"104-":{"count":22,"keywordTitle":"ipekyol","imageUrl":{"src":"660/-//ipekyol/products/FW2223/Koleksiyon/IW6220008040035.JPG","title":"ipekyol çift parça görünümlü kaban _kadin","marka":"ipekyol"}},"85-":{"count":26,"keywordTitle":"kısa","imageUrl":{"src":"products/2022/11/28/2627390/850b261a-ad92-4bd0-be0a-de1cd45b5971_size624x818.jpg","title":"koton  kısa peluş kaban cepli katlı yaka _kadin","marka":"koton"}},"92-":{"count":130,"keywordTitle":"koton","imageUrl":{"src":"products/2022/08/09/2564152/d4c67c30-a553-4ac9-80c2-0173b7662b1f_size624x818.jpg","title":"koton  kapüşonlu cepli kaban yün karışımlı _kadin","marka":"koton"}},"39-":{"count":8,"keywordTitle":"gömlek","imageUrl":{"src":"mnresize/600/-/pim/productimages/20222/6508181/v1/l_20222-w2km17z8-ge9_a.jpg","title":"lcwaikiki gömlek yaka kadın kaban _kadin","marka":"lcwaikiki"}},"135-":{"count":16,"keywordTitle":"600-700","imageUrl":{"src":"mnresize/600/-/pim/productimages/20202/4849501/v3/l_20202-0whg00z8-ct3_a.jpg","title":"lcwaikiki dik yaka uzun kollu kadın kaşe kaban _kadin","marka":"lcwaikiki"}},"93-":{"count":79,"keywordTitle":"lcwaikiki","imageUrl":{"src":"mnresize/600/-/pim/productimages/20222/5979472/v2/l_20222-w2ay82z8-shy-84-62-89-178_a.jpg","title":"lcwaikiki bisiklet yaka kendinden desenli uzun kollu kadın kaban _kadin","marka":"lcwaikiki"}},"105-":{"count":15,"keywordTitle":"machka","imageUrl":{"src":"mnresize/660/-//Machka/products/FW2223/MW6220008033180.jpg","title":"machka yün karışımlı kruvaze kaban _kadin","marka":"machka"}},"124-":{"count":16,"keywordTitle":"oxxo","imageUrl":{"src":"oxxo/ContentImages/Product/22k/22KOX-SUNAPCOAT/loose-fit-suet-kaban_argan-oil-kahverengi_1_detay.jpg","title":"oxxo kahverengi loose-fit süet kaban _kadin","marka":"oxxo"}},"127-":{"count":132,"keywordTitle":"patirti","imageUrl":{"src":"mnresize/-/750/g2147siyah_1.jpeg","title":"patirti kapşonlu siyah orta boy kadın  şişme kaban _kadin","marka":"patirti"}},"131-":{"count":17,"keywordTitle":"200-300","imageUrl":{"src":"Uploads/UrunResimleri/thumb/kadin-buklet-tek-dugmeli-cepli-kaban-m-b25824.jpg","title":"tozlu kadın buklet tek düğmeli cepli kaban mavi _kadin","marka":"tozlu"}},"120-":{"count":28,"keywordTitle":"perspective","imageUrl":{"src":"perspective/ContentImages/Product/2022-2023-sonbahar-kis/22250471-323/wender-kaban-0471_22250471-323_saks-lacivert_1_buyuk.jpg","title":"perspective bayan lacivert wender regular fit cep detaylı saks renk kaban _kadin","marka":"perspective"}},"107-":{"count":37,"keywordTitle":"roman","imageUrl":{"src":"638034200984632688-8681822287286_(2).jpg?width=500&height=750&bgcolor=white","title":"roman belden bağlamalı lacivert kadın kaban _kadin","marka":"roman"}},"206-":{"count":2,"keywordTitle":"tiffanytomato","imageUrl":{"src":"i/m/003/0031532_etnik-desenli-sal-yaka-kapitone-kaban.jpeg","title":"tiffanytomato etnik desenli şal yaka kapitone kaban _kadin","marka":"tiffanytomato"}},"114-":{"count":25,"keywordTitle":"tozlu","imageUrl":{"src":"Uploads/UrunResimleri/thumb/kadin-on-dugmeli-buklet-kaban-saksmavi-d614-f.jpg","title":"tozlu kadın ön düğmeli buklet kaban saksmavisi _kadin","marka":"tozlu"}},"110-":{"count":51,"keywordTitle":"zara","imageUrl":{"src":"/2023/V/0/1/p/2675/241/727/2/w/315/2675241727_1_1_1.jpg?ts=1671620174274","title":"zara CEPLİ OVERSIZE KABAN Vanilya _kadin","marka":"zara"}},"108-":{"count":17,"keywordTitle":"twist","imageUrl":{"src":"mnresize/800/-//Twist/products/FW2223/Koleksiyon/TW6220008048074.jpg","title":"twist süet görünümlü kaban                                                                                                                                süper twister indirimi _kadin","marka":"twist"}},"191-":{"count":1,"keywordTitle":"triko","imageUrl":{"src":"mnresize/800/-//Twist/products/FW2223/Koleksiyon/TW6220008027023.jpg","title":"twist triko mix kaban                                                                                                                                süper twister indirimi _kadin","marka":"twist"}},"112-":{"count":4,"keywordTitle":"vitrin","imageUrl":{"src":"/onden-dugmeli-cepli-teddy-kurk-kaban-kaban-vitrin-27453-14-O.jpg","title":"vitrin önden düğmeli cepli teddy kürk kaban _kadin","marka":"vitrin"}},"113-":{"count":2,"keywordTitle":"xint","imageUrl":{"src":"kadin-kaban-dugme-ve-cep-detayli-oversize-kaban-ekru-290399-kaban-xint-290399-65806-47-O.jpg","title":"xint kadın ekru düğme ve cep detaylı oversize kaban _kadin","marka":"xint"}}}