{"İç giyim":[{"keywords":"Iç Giyim,İç Çamaşırı,İç Giyim,Iç Çamaşırı,Iç Çamaşırı,Jartiyer\n","title":"İç Çamaşırı","exclude":"","keywordType":"category","groupName":"İç giyim","functionName":"five","index":"215-","count":55,"imageUrls":[{"src":"2019/07/05/403958/df67b60b-babd-45ff-9144-df05223fcd93_size500x762_quality100_cropCenter.jpg","title":"vakko v yaka lacivert iç giyim t-shirt _erkek","marka":"vakko"},{"src":"800/-/Assets/Branch/Originals/160622_0.jpeg","title":"colins baskılı siyah erkek iç giyim _erkek","marka":"colins"}]}],"Aksesuar":[{"keywords":"kemer,belt,kemeri","title":"kemer","exclude":"elbise,ceket,şort,tayt,etek,bluz,pantolon,bikini,mont,yelek,bot,kaban,kemer detaylı,çanta,terlik,kemerli","index":"2-","keywordType":"category","groupName":"Aksesuar","functionName":"four","count":554,"imageUrls":[{"src":"800/-/Assets/Branch/Originals/157538_0.jpeg","title":"colins erkek siyah kemer _erkek","marka":"colins"},{"src":"productimages/pnmjtbix.mui_IMG_19_2110089475649.jpg","title":"beymen Anderson's  Haki Kahverengi Örgü Dokulu Erkek Kemer _erkek","marka":"beymen"}]},{"keywords":"şapka,şapkası","title":"şapka","exclude":"","index":"8-","keywordType":"category","groupName":"Aksesuar","functionName":"four","count":1073,"imageUrls":[{"src":"productimages/z0qiwoyk.tzi_IMG_01_2110089501713.jpg","title":"beymen Rhude  Siyah Logo Detaylı Erkek Şapka _erkek","marka":"beymen"},{"src":"productimages/0xyxbonp.kut_IMG_01_2110075879895.jpg","title":"beymen New Era  New York Yankees 39 Thirty Siyah Erkek Şapka _erkek","marka":"beymen"}]},{"keywords":"şal","title":"şal","exclude":"Şal Yaka,Şal Detaylı,Şal desenli,şal kol,şallı,elbise","index":"13-","keywordType":"category","groupName":"Aksesuar","functionName":"four","count":80,"imageUrls":[{"src":"productimages/yp5xwsh0.0np_IMG_18_8683798087549.jpg","title":"beymen Network  Lacivert Çizgili Erkek Yün Şal _erkek","marka":"beymen"},{"src":"491/775/productimages/8683798172214_1.jpg","title":"network antrasit unisex keten şal _erkek","marka":"network"}]},{"keywords":"saat,saati","title":"saat","exclude":"","keywordType":"category","groupName":"Aksesuar","functionName":"four","index":"18-","count":973,"imageUrls":[{"src":"productimages/tkzsnlqt.tic_MP_44559c84-9368-446c-b13f-078a735f0a7e_1_85343101121157308549353427212_357.jpg","title":"beymen Versace  VRSCVE3A00320 Siyah Erkek Kol Saati _erkek","marka":"beymen"},{"src":"productimages/nupobsuq.gim_MP_8978af27-1dfe-4055-ad8a-b317f15158d6_1_49420191573139321428505211223_054.jpg","title":"beymen Emporio Armani  AR11188 Lacivert Erkek Kol Saati _erkek","marka":"beymen"}]},{"keywords":"çorap,Çorabı","title":"çorap","exclude":"sneaker, bot, çizme,ayakkabı,Çorap Model","index":"21-","keywordType":"category","groupName":"Aksesuar","functionName":"four","count":1868,"imageUrls":[{"src":"768/L8717AZ_NS_BK23_01_01.jpg","title":"defacto erkek bambu 2'li uzun çorap _erkek","marka":"defacto"},{"src":"mnresize/600/-/pim/productimages/20212/5528377/l_20212-w1ic49z8-k00_a.jpg","title":"lcwaikiki desenli erkek patik çorap 5'li _erkek","marka":"lcwaikiki"}]},{"keywords":"cüzdan","title":"cüzdan","exclude":"","index":"35-","keywordType":"category","groupName":"Aksesuar","functionName":"four","count":399,"imageUrls":[{"src":"productimages/hojiccxx.qck_IMG_01_8683798073528.jpg","title":"beymen Network  Kahverengi Erkek Deri Cüzdan _erkek","marka":"beymen"},{"src":"productimages/zdtwqaft.xiz_MP_3616af2e-9639-46f6-a974-7e9535c7c67e_1_75542554202017602351694450032_254.jpg","title":"beymen Roarcraft  Laodikya Logo Detaylı Zümrüt Yeşil Erkek Dikey Deri Cüzdan _erkek","marka":"beymen"}]},{"keywords":"gözlük,gözlüğü","title":"gözlük","exclude":"","keywordType":"category","groupName":"Aksesuar","functionName":"four","index":"44-","count":954,"imageUrls":[{"src":"productimages/kbpmitfg.r3z_IMG_01_2110081300307.jpg","title":"beymen Ray-Ban  Clubmaster Square Tortoise Unisex Güneş Gözlüğü _erkek","marka":"beymen"},{"src":"productimages/4ewzxyse.jnv_MP_e3f00c6e-5b9f-42b9-b52c-49729ea64455_1_00435510073157936176130221290_270.jpg","title":"beymen Roarcraft  Siyah Deri Güneş Gözlüğü Kılıfı _erkek","marka":"beymen"}]},{"keywords":"toka","title":"toka","exclude":"tokalı,etek,toka detaylı,elbise","keywordType":"category","groupName":"Aksesuar","functionName":"four","index":"59-","count":32,"imageUrls":[{"src":"768/V0626AZ_21SP_BK27_01_02.jpg","title":"defacto erkek dikdörtgen toka suni deri jean kemeri _erkek","marka":"defacto"},{"src":"768/W3092AZ_NS_BK27_01_02.jpg","title":"defacto erkek dikdörtgen toka suni deri jean kemeri _erkek","marka":"defacto"}]},{"keywords":"boyunluk","title":"boyunluk","exclude":"","keywordType":"category","groupName":"Aksesuar","functionName":"four","index":"71-","count":11,"imageUrls":[{"src":"491/775/productimages/8683798073290_1.jpg","title":"network lacivert unisex boyunluk _erkek","marka":"network"},{"src":"productimages/22crqs1u.yvn_IMG_01_2110088247247.jpg","title":"beymen Beymen Club  Lacivert Fermuarlı Erkek Yün Boyunluk _erkek","marka":"beymen"}]},{"keywords":"maske","title":"maske","exclude":"MI","keywordType":"category","groupName":"Aksesuar","functionName":"four","index":"72-","count":2,"imageUrls":[{"src":"800/-/Assets/Branch/Originals/143355_0.jpeg","title":"colins 3 katlı 5'li beyaz maske _erkek","marka":"colins"},{"src":"800/-/Assets/Branch/Originals/143355_0.jpeg","title":"colins 3 katlı 5'li beyaz maske _erkek","marka":"colins"}]},{"keywords":"fular","title":"fular","exclude":"fularlı desenli,elbise,gömlek,fular detaylı","keywordType":"category","groupName":"Aksesuar","functionName":"four","index":"81-","count":3,"imageUrls":[{"src":"productimages/ep4hz4uk.s2g_MP_b6afddf7-6445-4ae0-9e31-0e1fe994fe61_1_66630454052351923300492190255_194.jpg","title":"beymen Wabi Sabi  Ws X Mag Lacivert Oversize Comet Fular _erkek","marka":"beymen"},{"src":"productimages/ep4hz4uk.s2g_MP_b6afddf7-6445-4ae0-9e31-0e1fe994fe61_1_66630454052351923300492190255_194.jpg","title":"beymen Wabi Sabi  Ws X Mag Lacivert Oversize Comet Fular _erkek","marka":"beymen"}]},{"keywords":"saç","title":"saç aksesuar","exclude":"kazak,hırka,saç örgü","keywordType":"category","groupName":"Aksesuar","functionName":"four","index":"108-","count":2,"imageUrls":[{"src":"/2023/V/0/2/p/1271/425/555/2/w/315/1271425555_6_1_1.jpg?ts=1674210786462","title":"zara JAMES COFFMAN GRAFİK DESENLİ SAÇ BANDI çeşitli _erkek","marka":"zara"},{"src":"/2023/V/0/2/p/1271/425/555/2/w/315/1271425555_6_1_1.jpg?ts=1674210786462","title":"zara JAMES COFFMAN GRAFİK DESENLİ SAÇ BANDI çeşitli _erkek","marka":"zara"}]},{"keywords":"bere,beresi","title":"bere","exclude":"","keywordType":"category","groupName":"Aksesuar","functionName":"four","index":"109-","count":466,"imageUrls":[{"src":"768/R6055AZ_22WN_IN8_01_01.jpg","title":"defacto erkek basic triko bere _erkek","marka":"defacto"},{"src":"768/R7093AZ_20WN_YL1_01_01.jpg","title":"defacto erkek slogan desenli bere _erkek","marka":"defacto"}]},{"keywords":"bilezik","title":"bilezik","exclude":"","keywordType":"category","groupName":"Aksesuar","functionName":"four","index":"122-","count":32,"imageUrls":[{"src":"productimages/otlcmwen.stq_IMG_01_2110064383402.jpg","title":"beymen Boga  Single Lock Curved MS Long Mavi Erkek Bilezik _erkek","marka":"beymen"},{"src":"productimages/ezxusim3.gs3_IMG_01_2110090566923.jpg","title":"beymen AW by Atolyewolf  Oksit El Forsa Erkek Gümüş Bilezik _erkek","marka":"beymen"}]},{"keywords":"şemsiye","title":"şemsiye","exclude":"","keywordType":"category","groupName":"Aksesuar","functionName":"four","index":"123-","count":1,"imageUrls":[{"src":"productimages/zaq2de3n.a31_IMG_56_2110087582912.jpg","title":"beymen Beymen Club  Siyah Kontrast Logolu Şemsiye _erkek","marka":"beymen"},{"src":"productimages/zaq2de3n.a31_IMG_56_2110087582912.jpg","title":"beymen Beymen Club  Siyah Kontrast Logolu Şemsiye _erkek","marka":"beymen"}]},{"keywords":"atkı,Atki,Eşarp","title":"atkı,eşarp","exclude":"","keywordType":"category","groupName":"Aksesuar","functionName":"four","index":"136-","count":416,"imageUrls":[{"src":"productimages/hgtg4g40.coz_IMG_01_2110089648203.jpg","title":"beymen Begg&Co  ATKI _erkek","marka":"beymen"},{"src":"productimages/vb00g0qc.2om_IMG_01_2110089648043.jpg","title":"beymen Begg&Co  ATKI _erkek","marka":"beymen"}]},{"keywords":"çanta,çantası,bag,backpack,Çantasi","title":"çanta","exclude":"pantolon,baggy,ayakkabı,Çanta Baskılı,şort","keywordType":"category","groupName":"Aksesuar","functionName":"four","index":"147-","count":964,"imageUrls":[{"src":"productimages/akah2wjy.dh2_IMG_01_8699125681397.jpg","title":"beymen Beymen Hediye  Siyah Erkek Sırt Çantası _erkek","marka":"beymen"},{"src":"768/Y7062AZ_NS_BK27_01_01.jpg","title":"defacto erkek çapraz çanta _erkek","marka":"defacto"}]},{"keywords":"bileklik","title":"bileklik","exclude":"","keywordType":"category","groupName":"Aksesuar","functionName":"four","index":"149-","count":851,"imageUrls":[{"src":"productimages/0709001254_IMG_01_2110078883622.jpg","title":"beymen AtolyeWolf  Silver Rose Erkek Gümüş Rolo Bileklik _erkek","marka":"beymen"},{"src":"productimages/0709001254_IMG_01_2110077989936.jpg","title":"beymen Brace İstanbul  Bordo Kelepçe Formlu Erkek Gümüş Bileklik _erkek","marka":"beymen"}]},{"keywords":"küpe","title":"küpe","exclude":"","keywordType":"category","groupName":"Aksesuar","functionName":"four","index":"169-","count":8,"imageUrls":[{"src":"productimages/vf1uuxtj.uni_IMG_01_2110090566961.jpg","title":"beymen AW by Atolyewolf  El Forsa Erkek Gümüş Küpe _erkek","marka":"beymen"},{"src":"productimages/zbx5ywrl.3ck_IMG_01_2110090566978.jpg","title":"beymen AW by Atolyewolf  El Forsa Erkek Gümüş Küpe _erkek","marka":"beymen"}]},{"keywords":"eldiven","title":"eldiven","exclude":"eldiven detaylı,eldivenli","keywordType":"category","groupName":"Aksesuar","functionName":"four","index":"171-","count":146,"imageUrls":[{"src":"productimages/w1xfodh5.hmo_IMG_01_2110089508392.jpg","title":"beymen Ami  Gri Logo Nakışlı Erkek Yün Eldiven _erkek","marka":"beymen"},{"src":"768/Y3619AZ_22WN_BK23_01_02.jpg","title":"defacto erkek dokuma etiketli triko eldiven _erkek","marka":"defacto"}]},{"keywords":"bandana","title":"bandana","exclude":"","keywordType":"category","groupName":"Aksesuar","functionName":"four","index":"172-","count":10,"imageUrls":[{"src":"/2023/V/0/1/p/9967/401/450/22/w/315/9967401450_15_1_1.jpg?ts=1674043213430","title":"zara ŞAL DESENLİ JAKARLI BANDANA Bej _erkek","marka":"zara"},{"src":"productimages/tvnrpafi.zpj_IMG_01_2110087889776.jpg","title":"beymen Dolce&Gabbana  Dark Side Siyah Beyaz Bandana Desenli İpek Gömlek _erkek","marka":"beymen"}]},{"keywords":"kolye","title":"kolye","exclude":"","keywordType":"category","groupName":"Aksesuar","functionName":"four","index":"179-","count":284,"imageUrls":[{"src":"productimages/ziu3likc.45y_IMG_01_2110089934641.jpg","title":"beymen AtolyeWolf  Siyah Beyaz Sütun Erkek Gümüş Kolye _erkek","marka":"beymen"},{"src":"productimages/54d4ueml.zra_IMG_01_2110084382027.jpg","title":"beymen AtolyeWolf  Lacivert Şimşek Formlu Erkek Gümüş Kolye _erkek","marka":"beymen"}]},{"keywords":"yüzük","title":"yüzük","exclude":"","keywordType":"category","groupName":"Aksesuar","functionName":"four","index":"201-","count":103,"imageUrls":[{"src":"productimages/lsgyo0qb.umw_IMG_01_2110087434549.jpg","title":"beymen Academia  Smile Logo Detaylı Erkek Yüzük _erkek","marka":"beymen"},{"src":"productimages/a12vlv01.myp_IMG_01_2110066636032.jpg","title":"beymen Boga  King Kahverengi Taş Detaylı Erkek Gümüş Yüzük _erkek","marka":"beymen"}]},{"keywords":"parfüm","title":"parfüm","exclude":"","keywordType":"category","groupName":"Aksesuar","functionName":"four","index":"224-","count":57,"imageUrls":[{"src":"768/R4168AZ_NS_GN1_01_01.jpg","title":"defacto ocean aqua erkek parfüm 100 ml _erkek","marka":"defacto"},{"src":"768/K0339AZ_NS_BK21_01_04.jpg","title":"defacto dark lands erkek parfüm 100 ml _erkek","marka":"defacto"}]}],"Alt giyim":[{"keywords":"bermuda","title":"bermuda","exclude":"","index":"3-","keywordType":"category","groupName":"Alt giyim","functionName":"six","count":630,"imageUrls":[{"src":"768/W0293AZ_21HS_ER30_01_01.jpg","title":"defacto regular fit basic bermuda şort _erkek","marka":"defacto"},{"src":"mnresize/600/-/pim/productimages/20231/6386774/v1/l_20231-s3eg36z8-cvl-90-71-96-185_a.jpg","title":"lcwaikiki standart kalıp erkek bermuda şort _erkek","marka":"lcwaikiki"}]},{"keywords":"şort,Şortu","title":"şort","exclude":"şort korse,pijama","index":"6-","keywordType":"category","groupName":"Alt giyim","functionName":"six","count":3345,"imageUrls":[{"src":"products/2022/12/09/2632640/31d4d2e5-d0ce-4211-92ea-d4f0af70f49f_size624x818.jpg","title":"koton  basic şort beli bağcıklı slogan etiket baskılı cepli _erkek","marka":"koton"},{"src":"/2023/V/0/2/p/1943/300/611/2/w/315/1943300611_2_1_1.jpg?ts=1674216948540","title":"zara BASIC SPOR ŞORTU Mor _erkek","marka":"zara"}]},{"keywords":"tayt,taytı","title":"tayt","exclude":"pantolon","index":"89-","keywordType":"category","groupName":"Alt giyim","functionName":"six","count":32,"imageUrls":[{"src":"productimages/hu4dx25b.lfi_IMG_01_2110085945481.jpg","title":"beymen Cdlp  Siyah Beli Logo Bantlı Tayt _erkek","marka":"beymen"},{"src":"mnresize/600/-/pim/productimages/20212/5284018/v3/l_20212-w1af12z8-cvl_a.jpg","title":"lcwaikiki slim fit erkek spor tayt şort _erkek","marka":"lcwaikiki"}]},{"keywords":"eşofman","title":"eşofman","exclude":"","index":"97-","keywordType":"category","groupName":"Alt giyim","functionName":"six","count":2268,"imageUrls":[{"src":"mnresize/600/-/pim/productimages/20221/5429807/l_20221-s20924z8-cvl_a.jpg","title":"lcwaikiki standart kalıp erkek jogger eşofman altı _erkek","marka":"lcwaikiki"},{"src":"mnresize/600/-/pim/productimages/20212/5359332/v2/l_20212-w1da91z8-qu5_a.jpg","title":"lcwaikiki standart kalıp erkek jogger eşofman altı _erkek","marka":"lcwaikiki"}]},{"keywords":"pantolon,trousers,pantalon,pantolo,pantolonu,mom jean,Skinny Jean,Leg Jean","title":"pantolon","exclude":"pantolon görünümlü,kapri,gömlek","index":"126-","keywordType":"category","groupName":"Alt giyim","functionName":"six","count":5903,"imageUrls":[{"src":"/fb/a8/fba8c0a0b729234e5f68129bfe12bfc5230e92a1.jpg],origin[dam],category[],type[LOOKBOOK],res[z],hmver[1]&call=url[file:/product/main]","title":"hm slim fit takım pantolonu _erkek","marka":"hm"},{"src":"productimages/au1rvz3c.xxb_IMG_01_2400406659969.jpg","title":"beymen Network  JEAN PANTOLON _erkek","marka":"beymen"}]},{"keywords":"jogger","title":"jogger","exclude":"pantolon","index":"127-","keywordType":"category","groupName":"Alt giyim","functionName":"six","count":1278,"imageUrls":[{"src":"productimages/23fmxgfg.i5m_IMG_01_2110089187092.jpg","title":"beymen Off-White  Siyah Logo Detaylı Jogger Eşofman Altı _erkek","marka":"beymen"},{"src":"800/-/Assets/Branch/Originals/166144_0.jpeg","title":"colins orta bel jogger kahverengi erkek eşofman altı _erkek","marka":"colins"}]}],"Dış giyim":[{"keywords":"yelek","title":"yelek","exclude":"gömlek,elbise","index":"4-","keywordType":"category","groupName":"Dış giyim","functionName":"two","count":598,"imageUrls":[{"src":"/76/32/76325a51bd30bde13d2dbda7d32cb1cbfa292c22.jpg],origin[dam],category[],type[LOOKBOOK],res[z],hmver[1]&call=url[file:/product/main]","title":"hm regular fit dolgulu yelek _erkek","marka":"hm"},{"src":"mnresize/600/-/pim/productimages/20222/6129325/v1/l_20222-w2ft77z8-cvl-93-80-99-189_a.jpg","title":"lcwaikiki standart kalıp dik yaka erkek şişme yelek _erkek","marka":"lcwaikiki"}]},{"keywords":"pardösü,Pardesü","title":"pardösü","exclude":"","index":"10-","keywordType":"category","groupName":"Dış giyim","functionName":"two","count":33,"imageUrls":[{"src":"productimages/1mnsl14p.sny_IMG_01_2110090204399.jpg","title":"beymen Valentino  Rockstud Siyah Pardösü _erkek","marka":"beymen"},{"src":"productimages/pyog1exl.okf_IMG_01_2400406722069.jpg","title":"beymen Network  PARDÖSÜ _erkek","marka":"beymen"}]},{"keywords":"palto","title":"palto","exclude":"","index":"11-","keywordType":"category","groupName":"Dış giyim","functionName":"two","count":115,"imageUrls":[{"src":"productimages/xzz0levr.qfj_IMG_01_2110088081476.jpg","title":"beymen Beymen Club  Kamel Yün Klasik Palto _erkek","marka":"beymen"},{"src":"productimages/4cxilum5.vgq_IMG_01_2110089139657.jpg","title":"beymen Fendi  Siyah Çift Taraflı Yün Palto _erkek","marka":"beymen"}]},{"keywords":"parka","title":"parka","exclude":"","index":"14-","keywordType":"category","groupName":"Dış giyim","functionName":"two","count":91,"imageUrls":[{"src":"/ec/c4/ecc4685d9c920124ea54aadc7cb7ac634395e1f9.jpg],origin[dam],category[],type[LOOKBOOK],res[z],hmver[1]&call=url[file:/product/main]","title":"hm pamuklu kanvas parka _erkek","marka":"hm"},{"src":"productimages/5t4zv3kv.4g4_IMG_01_2110089176379.jpg","title":"beymen Carhartt  Taba Kapüşonlu Beli Büzgülü Parka _erkek","marka":"beymen"}]},{"keywords":"blazer","title":"blazer","exclude":"blazer tasarımlı,sneaker","index":"34-","keywordType":"category","groupName":"Dış giyim","functionName":"two","count":216,"imageUrls":[{"src":"491/775/productimages/8683798096923_1.jpg","title":"network lacivert blazer ceket _erkek","marka":"network"},{"src":"productimages/fyyg5uey.1fe_IMG_01_2110087799709.jpg","title":"beymen Beymen Club  Drop 6 Siyah Kaşe Blazer _erkek","marka":"beymen"}]},{"keywords":"ceket,ceketi,Triko Ceket,Çeket","title":"ceket","exclude":"ceket yaka, elbise,ceket tasarımlı,gömlek,dik yaka,mont","index":"86-","keywordType":"category","groupName":"Dış giyim","functionName":"two","count":1226,"imageUrls":[{"src":"mnresize/600/-/pim/productimages/20222/5938772/v1/l_20222-w29043z8-309_a.jpg","title":"lcwaikiki standart kalıp erkek jean ceket _erkek","marka":"lcwaikiki"},{"src":"productimages/knr0tk5m.rnj_IMG_01_2110086232818.jpg","title":"beymen Canali  Lacivert Yün Ceket _erkek","marka":"beymen"}]},{"keywords":"kaban","title":"kaban","exclude":"","index":"151-","keywordType":"category","groupName":"Dış giyim","functionName":"two","count":141,"imageUrls":[{"src":"productimages/i1g1oxy1.zaw_IMG_01_2110091099307.jpg","title":"beymen Brunello Cucinelli  Mavi Kapüşonlu Beli Büzgülü Kaban _erkek","marka":"beymen"},{"src":"productimages/cql40fvf.j1c_IMG_01_2110088866806.jpg","title":"beymen Kiton  Bordo Kapüşonlu Puff Kaban _erkek","marka":"beymen"}]},{"keywords":"mont,sweatmont,trençmont,montu","title":"mont","exclude":"","index":"161-","keywordType":"category","groupName":"Dış giyim","functionName":"two","count":1357,"imageUrls":[{"src":"productimages/evi0ygdw.5ct_IMG_01_8683798051373.jpg","title":"beymen Network  Ekru Mont _erkek","marka":"beymen"},{"src":"768/R0216AZ_20WN_BK27_01_01.jpg","title":"defacto slim fit kapüşonlu şişme mont _erkek","marka":"defacto"}]},{"keywords":"yağmurluk","title":"yağmurluk","exclude":"","index":"189-","keywordType":"category","groupName":"Dış giyim","functionName":"two","count":115,"imageUrls":[{"src":"products/2022/08/25/2574046/608c53d8-20b2-4138-bef3-d03e717bde8a_size624x818.jpg","title":"koton  kapşonlu fermuarlı yağmurluk su geçirmez _erkek","marka":"koton"},{"src":"mnresize/600/-/pim/productimages/20221/5448746/l_20221-s21408z8-j2y_a.jpg","title":"lcwaikiki standart kalıp kapüşonlu erkek yağmurluk _erkek","marka":"lcwaikiki"}]},{"keywords":"trençkot,trenç,Trenchcoat","title":"trençkot","exclude":"","index":"190-","keywordType":"category","groupName":"Dış giyim","functionName":"two","count":1,"imageUrls":[{"src":"491/775/productimages/2400406659693_1.jpg","title":"network kahverengi trençkot _erkek","marka":"network"},{"src":"491/775/productimages/2400406659693_1.jpg","title":"network kahverengi trençkot _erkek","marka":"network"}]}],"Ev giyim":[{"keywords":"sabahlık","title":"sabahlık","exclude":"","index":"7-","keywordType":"category","groupName":"Ev giyim","functionName":"one","count":4,"imageUrls":[{"src":"768/X9421AZ_22AU_NV135_01_01.jpg","title":"defacto regular fit şal yaka polar sabahlık _erkek","marka":"defacto"},{"src":"768/X9421AZ_22AU_NV135_01_01.jpg","title":"defacto regular fit şal yaka polar sabahlık _erkek","marka":"defacto"}]},{"keywords":"pijama","title":"pijama","exclude":"pijama yaka","index":"66-","keywordType":"category","groupName":"Ev giyim","functionName":"one","disabled":false,"count":676,"imageUrls":[{"src":"mnresize/600/-/pim/productimages/20221/5556864/l_20221-s25163z8-hen_a.jpg","title":"lcwaikiki standart kalıp erkek pijama alt _erkek","marka":"lcwaikiki"},{"src":"480/720/pentiimages/PHZ0RVG622SK-WT3_front.jpg","title":"penti optik beyaz daddy team family pijama seti _erkek","marka":"penti"}]},{"keywords":"Plaj","title":"Plaj","exclude":"","keywordType":"category","groupName":"Ev giyim","functionName":"one","index":"219-","count":124,"imageUrls":[{"src":"productimages/ztkzdtc1.rdv_IMG_01_2110090661307.jpg","title":"beymen Polo Ralph Lauren  Kamuflaj Desenli Logo Detaylı Erkek Plaj Terliği _erkek","marka":"beymen"},{"src":"productimages/wuov51e0.aku_IMG_01_2110083522370.jpg","title":"beymen Havaianas  Top Marvel Supermen Baskılı Erkek Plaj Terliği _erkek","marka":"beymen"}]}],"Üst giyim":[{"keywords":"atlet,atleti","title":"atlet","exclude":"tunik","index":"9-","keywordType":"category","groupName":"Üst giyim","functionName":"seven","count":492,"imageUrls":[{"src":"768/Y4323AZ_22SM_WT80_01_02.jpg","title":"defacto defacto fit comfort fit kapüşonlu spor atlet _erkek","marka":"defacto"},{"src":"mnresize/600/-/pim/productimages/20211/5151317/v1/l_20211-s1i173z8-q6k_a1.jpg","title":"lcwaikiki bisiklet yaka baskılı pamuklu erkek atlet _erkek","marka":"lcwaikiki"}]},{"keywords":"kimono","title":"kimono","exclude":"elbise","index":"47-","keywordType":"category","groupName":"Üst giyim","functionName":"seven","count":2,"imageUrls":[{"src":"productimages/o2jkqzwj.j4q_IMG_01_2110085325771.jpg","title":"beymen Academia  Siyah Kimono Abiye Ceket _erkek","marka":"beymen"},{"src":"productimages/o2jkqzwj.j4q_IMG_01_2110085325771.jpg","title":"beymen Academia  Siyah Kimono Abiye Ceket _erkek","marka":"beymen"}]},{"keywords":"hırka,Hirka","title":"hırka","exclude":"tunik","index":"48-","keywordType":"category","groupName":"Üst giyim","functionName":"seven","count":695,"imageUrls":[{"src":"mnresize/600/-/pim/productimages/20222/6181110/v1/l_20222-w2gy42z8-lal_a.jpg","title":"lcwaikiki rahat kalıp kapüşonlu erkek spor hırka _erkek","marka":"lcwaikiki"},{"src":"productimages/gmvfxitb.f2a_IMG_01_2110089545885.jpg","title":"beymen Howlin  Back From The Grave Örgü Dokulu Yün Triko Hırka _erkek","marka":"beymen"}]},{"keywords":"pelerin","title":"pelerin","exclude":"","keywordType":"category","groupName":"Üst giyim","functionName":"seven","index":"94-","count":1,"imageUrls":[{"src":"productimages/mp0ffs5w.40z_IMG_01_2110089515055.jpg","title":"beymen Jw Anderson  Yeşil Mavi Pelerin Detaylı Bomber Mont _erkek","marka":"beymen"},{"src":"productimages/mp0ffs5w.40z_IMG_01_2110089515055.jpg","title":"beymen Jw Anderson  Yeşil Mavi Pelerin Detaylı Bomber Mont _erkek","marka":"beymen"}]},{"keywords":"bluz,Blouse","title":"bluz","exclude":"","index":"113-","keywordType":"category","groupName":"Üst giyim","functionName":"seven","count":11,"imageUrls":[{"src":"/2023/V/0/2/p/0304/420/526/2/w/315/0304420526_6_1_1.jpg?ts=1673887431137","title":"zara FİTİLLİ ÖRGÜ BLUZ Açık yeşil _erkek","marka":"zara"},{"src":"mnresize/-/750/BDY0470D1550BRD_1.jpeg","title":"patirti erkek bluz bordo _erkek","marka":"patirti"}]},{"keywords":"tişört,tshirt,t-shirt,penye,T Shirt,Tshırt,T-Shırt","title":"tişört","exclude":"Pantolon","index":"114-","keywordType":"category","groupName":"Üst giyim","functionName":"seven","disabled":false,"count":11481,"imageUrls":[{"src":"mnresize/600/-/pim/productimages/20221/5912992/l_20221-s2jn61z8-fhp_a.jpg","title":"lcwaikiki bisiklet yaka kısa kollu smileyworld baskılı erkek tişört _erkek","marka":"lcwaikiki"},{"src":"mnresize/600/-/pim/productimages/20222/5930042/v1/l_20222-w28414z8-rdv_a.jpg","title":"lcwaikiki bisiklet yaka kısa kollu erkek spor tişört _erkek","marka":"lcwaikiki"}]},{"keywords":"süveter","title":"süveter","exclude":"tunik","index":"140-","keywordType":"category","groupName":"Üst giyim","functionName":"seven","count":22,"imageUrls":[{"src":"productimages/akr51vxz.fxz_IMG_01_2110083434529.jpg","title":"beymen Beymen Collection  Antrasit V Yaka Süveter _erkek","marka":"beymen"},{"src":"768/W6630AZ_22AU_BK27_01_03.jpg","title":"defacto relax fit süveter _erkek","marka":"defacto"}]},{"keywords":"gömlek,gömle,gömleği,gomlek","title":"gömlek","exclude":"gömlek yaka","index":"153-","keywordType":"category","groupName":"Üst giyim","functionName":"seven","count":6720,"imageUrls":[{"src":"mnresize/600/-/pim/productimages/20212/5255549/l_20212-w18100z8-lmr_a.jpg","title":"lcwaikiki slim fit uzun kollu ekose gabardin erkek gömlek _erkek","marka":"lcwaikiki"},{"src":"mnresize/600/-/pim/productimages/20201/3868792/l_20201-0s3074z8-lu7_a.jpg","title":"lcwaikiki poplin erkek gömlek _erkek","marka":"lcwaikiki"}]},{"keywords":"kazak","title":"kazak","exclude":"tunik","index":"191-","keywordType":"category","groupName":"Üst giyim","functionName":"seven","count":3617,"imageUrls":[{"src":"mnresize/600/-/pim/productimages/20222/5906249/v1/l_20222-w26301z8-e3n-102-88-96-190_a.jpg","title":"lcwaikiki dik yaka uzun kollu erkek triko kazak _erkek","marka":"lcwaikiki"},{"src":"productimages/ppumnz1r.kki_IMG_01_2110089351370.jpg","title":"beymen MCQ  Gri Etnik Desen Jakarlı Kazak _erkek","marka":"beymen"}]},{"keywords":"sweatshirt,sweat,sweatshırt","title":"sweatshirt","exclude":"","index":"192-","keywordType":"category","groupName":"Üst giyim","functionName":"seven","count":5033,"imageUrls":[{"src":"mnresize/600/-/pim/productimages/20202/4861068/l_20202-0whn21z8-qm0_a.jpg","title":"lcwaikiki bisiklet yaka baskılı sweatshirt _erkek","marka":"lcwaikiki"},{"src":"products/2022/05/16/1253334/17c448ac-27ad-44c2-9a40-9b648b348f1c_size624x818.jpg","title":"koton  dokulu etiketli sweatshirt _erkek","marka":"koton"}]},{"keywords":"takım","title":"takım","exclude":"","keywordType":"category","groupName":"Üst giyim","functionName":"seven","index":"203-","count":439,"imageUrls":[{"src":"productimages/szb2dzoe.s2l_IMG_01_2110088546845.jpg","title":"beymen Canali  Gri Kareli Yün Takım Elbise _erkek","marka":"beymen"},{"src":"768/Y1545AZ_22SM_WT32_01_02.jpg","title":"defacto regular fit bisiklet yaka 2'li takım _erkek","marka":"defacto"}]},{"keywords":"abiye,gelinlik","title":"abiye","exclude":"","keywordType":"category","groupName":"Üst giyim","functionName":"seven","index":"209-","count":1,"imageUrls":[{"src":"productimages/o2jkqzwj.j4q_IMG_01_2110085325771.jpg","title":"beymen Academia  Siyah Kimono Abiye Ceket _erkek","marka":"beymen"},{"src":"productimages/o2jkqzwj.j4q_IMG_01_2110085325771.jpg","title":"beymen Academia  Siyah Kimono Abiye Ceket _erkek","marka":"beymen"}]},{"keywords":"tulum,tulumu,Jumpsuit","title":"tulum","exclude":"","keywordType":"category","groupName":"Üst giyim","functionName":"seven","index":"210-","count":7,"imageUrls":[{"src":"/0a/54/0a54fc6af61e541e1228113377307c1ff4d91152.jpg],origin[dam],category[],type[LOOKBOOK],res[z],hmver[2]&call=url[file:/product/main]","title":"hm relaxed fit kot tulum _erkek","marka":"hm"},{"src":"/f0/bf/f0bf8b8730d5e32cae987d40a34b087f91d1f0c6.jpg],origin[dam],category[],type[LOOKBOOK],res[z],hmver[1]&call=url[file:/product/main]","title":"hm relaxed fit tulum _erkek","marka":"hm"}]},{"keywords":"body","title":"body","exclude":"Fantazi","keywordType":"category","groupName":"Üst giyim","functionName":"seven","index":"216-","count":23,"imageUrls":[{"src":"Uploads/UrunResimleri/thumb/beyaz-berrak-erkek-sifir-yaka-yarim-ko-b34fb8.jpg","title":"tozlu berrak erkek sıfır yaka yarım kollu body atlet beyaz _erkek","marka":"tozlu"},{"src":"Uploads/UrunResimleri/thumb/beyaz-berrak-erkek-sifir-yaka-yarim-ko-b34fb8.jpg","title":"tozlu berrak erkek sıfır yaka yarım kollu body atlet beyaz _erkek","marka":"tozlu"}]},{"keywords":"Takım Elbise","title":"takım elbise","exclude":"","keywordType":"category","groupName":"Üst giyim","functionName":"seven","index":"226-","count":275,"imageUrls":[{"src":"productimages/dyglhlg5.yqx_IMG_01_2110088546678.jpg","title":"beymen Canali  Gri Kareli Yün Takım Elbise _erkek","marka":"beymen"},{"src":"productimages/e1nzl5fr.lvg_IMG_01_2110085439423.jpg","title":"beymen Beymen Collection  Drop 7 Gri Yün Takım Elbise _erkek","marka":"beymen"}]}],"Ayakkabı":[{"keywords":"loafer","title":"loafer","exclude":"","keywordType":"category","groupName":"Ayakkabı","functionName":"nine","index":"32-","count":338,"imageUrls":[{"src":"productimages/c2sd2lnd.imo_IMG_11_2110088700018.jpg","title":"beymen Giuseppe Zanotti  Siyah Logolu Erkek Deri Loafer _erkek","marka":"beymen"},{"src":"productimages/2muyka3u.rhm_IMG_01_2110090764176.jpg","title":"beymen Christian Louboutin  Siyah Erkek Deri Loafer _erkek","marka":"beymen"}]},{"keywords":"terlik,terliği,terli","title":"terlik","exclude":"","keywordType":"category","groupName":"Ayakkabı","functionName":"nine","index":"33-","count":553,"imageUrls":[{"src":"productimages/r4ddesad.ztm_IMG_01_2110090266601.jpg","title":"beymen Bottega Veneta  Siyah Erkek Terlik _erkek","marka":"beymen"},{"src":"productimages/llwxqgvw.rkv_IMG_01_2110087534713.jpg","title":"beymen Birkenstock  Arizona Yeşil Erkek Terlik _erkek","marka":"beymen"}]},{"keywords":"makosen","title":"makosen","exclude":"","keywordType":"category","groupName":"Ayakkabı","functionName":"nine","index":"45-","count":16,"imageUrls":[{"src":"/2023/V/1/2/p/2601/120/800/2/w/315/2601120800_6_1_1.jpg?ts=1671447459827","title":"zara BANTLI MAKOSEN Siyah _erkek","marka":"zara"},{"src":"/2023/V/1/2/p/2604/120/700/2/w/315/2604120700_6_1_1.jpg?ts=1671699945826","title":"zara PÜSKÜLLÜ DERİ MAKOSEN Kahverengi _erkek","marka":"zara"}]},{"keywords":"sneaker,Spor ayakkabı,Bağcıklı Ayakkabı,Spor Ayakkabi","title":"Spor (sneaker)","exclude":"","keywordType":"category","groupName":"Ayakkabı","functionName":"nine","index":"70-","count":2159,"imageUrls":[{"src":"productimages/dicxc5ok.ss3_IMG_01_2110088520876.jpg","title":"beymen Christian Louboutin  Rantulow Koyu Gri Erkek Deri Sneaker _erkek","marka":"beymen"},{"src":"productimages/yfoeusme.ll2_IMG_01_2110091152187.jpg","title":"beymen Giuseppe Zanotti  Mavi Erkek Süet Sneaker _erkek","marka":"beymen"}]},{"keywords":"babet","title":"babet","exclude":"","index":"115-","keywordType":"category","groupName":"Ayakkabı","functionName":"nine","count":114,"imageUrls":[{"src":"768/V6913AZ_21AU_GR2_01_01.jpg","title":"defacto erkek 3'lü babet çorap _erkek","marka":"defacto"},{"src":"768/W7904AZ_NS_KR1_01_01.jpg","title":"defacto erkek desenli pamuklu 3'lü babet çorap _erkek","marka":"defacto"}]},{"keywords":"stiletto,heeled shoes,topuklu,Platform Ayakkabı,Topuk Ayakkabı","title":"topuklu (stiletto)","exclude":"","keywordType":"category","groupName":"Ayakkabı","functionName":"nine","index":"148-","count":2,"imageUrls":[{"src":"/2022/I/1/2/p/2085/020/800/2/w/315/2085020800_6_1_1.jpg?ts=1666262501339","title":"zara TOPUKLU DERİ ÇİZME Siyah _erkek","marka":"zara"},{"src":"/2022/I/1/2/p/2085/020/800/2/w/315/2085020800_6_1_1.jpg?ts=1666262501339","title":"zara TOPUKLU DERİ ÇİZME Siyah _erkek","marka":"zara"}]},{"keywords":"sandalet","title":"sandalet","exclude":"","keywordType":"category","groupName":"Ayakkabı","functionName":"nine","index":"160-","count":80,"imageUrls":[{"src":"productimages/ovtpifjo.nwj_IMG_05_2110088887214.jpg","title":"beymen Keen  Uneek Siyah Erkek Sandalet _erkek","marka":"beymen"},{"src":"/2023/V/1/2/p/2712/120/800/2/w/315/2712120800_6_1_1.jpg?ts=1674734798434","title":"zara BANTLI DERİ SANDALET Siyah _erkek","marka":"zara"}]},{"keywords":"bot,botu,boots","title":"bot","exclude":"bot yaka","keywordType":"category","groupName":"Ayakkabı","functionName":"nine","index":"170-","count":605,"imageUrls":[{"src":"productimages/utatoz00.lpi_IMG_06_2110088630148.jpg","title":"beymen Academia  Kahverengi Erkek Nubuk Bot _erkek","marka":"beymen"},{"src":"productimages/ogjfefeb.uhj_IMG_12_2110089877337.jpg","title":"beymen AllSaints  Siyah Erkek Deri Bot _erkek","marka":"beymen"}]},{"keywords":"deri ayakkabı","title":"deri ayakkabı","exclude":"","keywordType":"category","groupName":"Ayakkabı","functionName":"nine","index":"214-","count":335,"imageUrls":[{"src":"productimages/y5abpgzs.zjo_IMG_06_2110089460829.jpg","title":"beymen Moreschi  Siyah Erkek Deri Ayakkabı _erkek","marka":"beymen"},{"src":"productimages/ivgqlgu2.pjo_IMG_06_2110088616715.jpg","title":"beymen Beymen Collection  Bordo Erkek Deri Ayakkabı _erkek","marka":"beymen"}]}],"Diger":[{"keywords":"diger","title":"diger","exclude":"","keywordType":"category","groupName":"Diger","functionName":"diger","index":"212-","count":6813,"imageUrls":[{"src":"2023/02/10/1437212/9285248f-25e4-44ae-9e84-d084b03274df_size500x762_quality100_cropCenter.jpg","title":"vakko diyagonal çizgili ipek kravat _erkek diger","marka":"vakko"},{"src":"/2023/V/1/2/p/2520/120/120/2/w/315/2520120120_6_1_1.jpg?ts=1674142898887","title":"zara TIRTIKLI TABANLI AYAKKABI Kemik Beyazı _erkek diger","marka":"zara"}]}],"diger":[]}